LICENSE
MANIFEST.in
README.rst
setup.py
django_stachoutils/__init__.py
django_stachoutils/csv_utf8.py
django_stachoutils/decorators.py
django_stachoutils/log.py
django_stachoutils/middlewares.py
django_stachoutils/models.py
django_stachoutils/options.py
django_stachoutils/profiler.py
django_stachoutils/shortcuts.py
django_stachoutils/sql.py
django_stachoutils/storage.py
django_stachoutils.egg-info/PKG-INFO
django_stachoutils.egg-info/SOURCES.txt
django_stachoutils.egg-info/dependency_links.txt
django_stachoutils.egg-info/requires.txt
django_stachoutils.egg-info/top_level.txt
django_stachoutils/forms/__init__.py
django_stachoutils/forms/fields.py
django_stachoutils/forms/models.py
django_stachoutils/forms/nested.py
django_stachoutils/forms/widgets.py
django_stachoutils/management/__init__.py
django_stachoutils/management/commands/__init__.py
django_stachoutils/management/commands/dumpdata_related.py
django_stachoutils/management/commands/hotspot_report.py
django_stachoutils/management/commands/sync_permissions.py
django_stachoutils/static/django_stachoutils/css/admin_extras.css
django_stachoutils/static/django_stachoutils/css/commons.css
django_stachoutils/static/django_stachoutils/css/forms.css
django_stachoutils/static/django_stachoutils/img/filters.png
django_stachoutils/static/django_stachoutils/img/icon-inactive-no.gif
django_stachoutils/static/django_stachoutils/img/icon-inactive-yes.gif
django_stachoutils/static/django_stachoutils/img/icon-no.gif
django_stachoutils/static/django_stachoutils/img/icon-yes.gif
django_stachoutils/static/django_stachoutils/img/processing.png
django_stachoutils/static/django_stachoutils/img/sprites.png
django_stachoutils/static/django_stachoutils/js/admin_extras.js
django_stachoutils/static/django_stachoutils/js/change_list.js
django_stachoutils/static/django_stachoutils/js/editeur.js
django_stachoutils/static/django_stachoutils/js/forms.js
django_stachoutils/static/django_stachoutils/js/jquery.AjaxCSRFprotection.js
django_stachoutils/static/django_stachoutils/js/jquery.charcounter.js
django_stachoutils/static/django_stachoutils/js/jquery.fieldselection.js
django_stachoutils/static/django_stachoutils/poshytip/jquery.poshytip.js
