Metadata-Version: 1.2
Name: django-stachoutils
Version: 4.7.0
Summary: Commons for Django
Home-page: https://github.com/Starou/django-stachoutils
Author: Stanislas Guerra
Author-email: stan@slashdev.me
License: BSD Licence
Project-URL: Source Code, https://github.com/Starou/django-stachoutils
Project-URL: Issue Tracker, https://github.com/Starou/django-stachoutils/issues
Platform: UNKNOWN
Classifier: Environment :: Web Environment
Classifier: Framework :: Django
Classifier: Intended Audience :: Developers
Classifier: License :: OSI Approved :: BSD License
Classifier: Operating System :: OS Independent
Classifier: Programming Language :: Python
Classifier: Programming Language :: Python :: 3
Classifier: Programming Language :: Python :: 3.9
Classifier: Topic :: Internet :: WWW/HTTP
Classifier: Topic :: Internet :: WWW/HTTP :: Dynamic Content
